<?xml version="1.0" encoding="UTF-8"?>
<objects serializationModel="Studio.02.02.00">
	<object class="AudioFile" id="{4efe2b5a-685a-49eb-9d19-edc758f2094f}">
		<property name="assetPath">
			<value>UI/UI_Menu_Close/UI_Menu_Close_01.wav</value>
		</property>
		<property name="frequencyInKHz">
			<value>48</value>
		</property>
		<property name="channelCount">
			<value>2</value>
		</property>
		<property name="length">
			<value>0.66666666666666663</value>
		</property>
		<relationship name="masterAssetFolder">
			<destination>{9770f1ba-763d-4a07-a99d-0700eaaf3b3b}</destination>
		</relationship>
	</object>
</objects>
